.DS_Store
AlteryxConnector/__init__.py
AlteryxConnector/main.py
AlteryxConnector-0.3.dist-info/METADATA
AlteryxConnector-0.3.dist-info/WHEEL
AlteryxConnector-0.3.dist-info/entry_points.txt
AlteryxConnector-0.3.dist-info/top_level.txt
AlteryxConnector-0.3.dist-info/RECORD
