Metadata-Version: 2.1
Name: AlteryxConnector
Version: 0.3
